odoo/addons/contract_mandate/README.rst
odoo/addons/contract_mandate/__init__.py
odoo/addons/contract_mandate/__manifest__.py
odoo/addons/contract_mandate/i18n/ca.po
odoo/addons/contract_mandate/i18n/contract_mandate.pot
odoo/addons/contract_mandate/i18n/de.po
odoo/addons/contract_mandate/i18n/el_GR.po
odoo/addons/contract_mandate/i18n/es.po
odoo/addons/contract_mandate/i18n/es_AR.po
odoo/addons/contract_mandate/i18n/es_MX.po
odoo/addons/contract_mandate/i18n/fi.po
odoo/addons/contract_mandate/i18n/fr.po
odoo/addons/contract_mandate/i18n/gl.po
odoo/addons/contract_mandate/i18n/hr.po
odoo/addons/contract_mandate/i18n/hr_HR.po
odoo/addons/contract_mandate/i18n/hu.po
odoo/addons/contract_mandate/i18n/it.po
odoo/addons/contract_mandate/i18n/nl.po
odoo/addons/contract_mandate/i18n/pt.po
odoo/addons/contract_mandate/i18n/pt_BR.po
odoo/addons/contract_mandate/i18n/pt_PT.po
odoo/addons/contract_mandate/i18n/ro.po
odoo/addons/contract_mandate/i18n/sk_SK.po
odoo/addons/contract_mandate/i18n/sl.po
odoo/addons/contract_mandate/i18n/zh_CN.po
odoo/addons/contract_mandate/models/__init__.py
odoo/addons/contract_mandate/models/contract.py
odoo/addons/contract_mandate/readme/CONFIGURATION.rst
odoo/addons/contract_mandate/readme/CONTRIBUTORS.rst
odoo/addons/contract_mandate/readme/DESCRIPTION.rst
odoo/addons/contract_mandate/readme/USAGE.rst
odoo/addons/contract_mandate/static/description/icon.png
odoo/addons/contract_mandate/static/description/index.html
odoo/addons/contract_mandate/tests/__init__.py
odoo/addons/contract_mandate/tests/test_contract_mandate.py
odoo/addons/contract_mandate/views/contract_view.xml
odoo14_addon_contract_mandate-14.0.1.0.1.dist-info/METADATA
odoo14_addon_contract_mandate-14.0.1.0.1.dist-info/WHEEL
odoo14_addon_contract_mandate-14.0.1.0.1.dist-info/top_level.txt
odoo14_addon_contract_mandate-14.0.1.0.1.dist-info/RECORD
