Metadata-Version: 2.1
Name: odoo14-addon-contract-mandate
Version: 14.0.1.0.1
Summary: Mandate in contracts and their invoices
Home-page: https://github.com/OCA/contract
Author: Odoo Community Association (OCA), Tecnativa
Author-email: support@odoo-community.org
License: AGPL-3
Platform: UNKNOWN
Classifier: Programming Language :: Python
Classifier: Framework :: Odoo
Classifier: Framework :: Odoo :: 14.0
Classifier: License :: OSI Approved :: GNU Affero General Public License v3
Requires-Python: >=3.6
Requires-Dist: odoo14-addon-account-banking-mandate
Requires-Dist: odoo14-addon-contract-payment-mode
Requires-Dist: odoo (<14.1dev,>=14.0a)
